LICENSE
MANIFEST.in
README.md
setup.py
reinit_migrations/__init__.py
reinit_migrations/admin.py
reinit_migrations/apps.py
reinit_migrations/models.py
reinit_migrations/tests.py
reinit_migrations/views.py
reinit_migrations.egg-info/PKG-INFO
reinit_migrations.egg-info/SOURCES.txt
reinit_migrations.egg-info/dependency_links.txt
reinit_migrations.egg-info/top_level.txt
reinit_migrations/management/__init__.py
reinit_migrations/management/commands/__init__.py
reinit_migrations/management/commands/reinit_migrations.py
reinit_migrations/migrations/__init__.py